{
  "@type" : "TEMPLATE",
  "uid" : "809eaf5e-5c59-42c0-8ebf-2050114e54d6",
  "description" : {
    "@type" : "RESOURCE_DESCRIPTION",
    "originalAuthor" : {
      "name" : "Erik Sundvall",
      "organisation" : "Karolinska University hospital + Institute & Linköping University, Sweden",
      "email" : "erik.sundvall@regionstockholm.se",
      "date" : "2021-12-14"
    },
    "otherContributors" : [ ],
    "lifecycleState" : {
      "codeString" : "unmanaged"
    },
    "ipAcknowledgements" : { },
    "references" : { },
    "conversionDetails" : { },
    "otherDetails" : {
      "licence" : "",
      "custodian_organisation" : "",
      "original_namespace" : "",
      "original_publisher" : "",
      "custodian_namespace" : "",
      "sem_ver" : "1.0.0",
      "build_uid" : "5746ba87-6c50-487d-ae95-843cd2a76da7",
      "MD5-CAM-1.0.1" : "36b0ef9bd6f187e5bd7fdbbdc642d839",
      "PARENT:MD5-CAM-1.0.1" : "56687785A4AEF4D2BE503626E5D494CB"
    },
    "details" : {
      "de" : {
        "@type" : "RESOURCE_DESCRIPTION_ITEM",
        "language" : {
          "terminologyId" : {
            "value" : "ISO_639-1"
          },
          "codeString" : "de"
        },
        "keywords" : [ ],
        "originalResourceUri" : { },
        "otherDetails" : { }
      },
      "sv" : {
        "@type" : "RESOURCE_DESCRIPTION_ITEM",
        "language" : {
          "terminologyId" : {
            "value" : "ISO_639-1"
          },
          "codeString" : "sv"
        },
        "keywords" : [ ],
        "originalResourceUri" : { },
        "otherDetails" : { }
      },
      "nb" : {
        "@type" : "RESOURCE_DESCRIPTION_ITEM",
        "language" : {
          "terminologyId" : {
            "value" : "ISO_639-1"
          },
          "codeString" : "nb"
        },
        "keywords" : [ ],
        "originalResourceUri" : { },
        "otherDetails" : { }
      },
      "en" : {
        "@type" : "RESOURCE_DESCRIPTION_ITEM",
        "language" : {
          "terminologyId" : {
            "value" : "ISO_639-1"
          },
          "codeString" : "en"
        },
        "keywords" : [ ],
        "originalResourceUri" : { },
        "otherDetails" : { }
      }
    }
  },
  "parentArchetypeId" : "openEHR-EHR-CLUSTER.organisation.v0",
  "differential" : true,
  "archetypeId" : {
    "@type" : "ARCHETYPE_HRID",
    "value" : "openEHR-EHR-CLUSTER.t_organisation.v0"
  },
  "definition" : {
    "@type" : "C_COMPLEX_OBJECT",
    "rmTypeName" : "CLUSTER",
    "nodeId" : "at0000.1",
    "attributes" : [ {
      "@type" : "C_ATTRIBUTE",
      "rmAttributeName" : "items",
      "children" : [ {
        "@type" : "C_COMPLEX_OBJECT",
        "rmTypeName" : "ELEMENT",
        "nodeId" : "at0003.1",
        "attributes" : [ {
          "@type" : "C_ATTRIBUTE",
          "rmAttributeName" : "value",
          "children" : [ {
            "@type" : "C_COMPLEX_OBJECT",
            "rmTypeName" : "DV_IDENTIFIER",
            "defaultValue" : {
              "type" : "urn:oid:1.2.752.29.4.19",
              "@type" : "DV_IDENTIFIER"
            },
            "attributes" : [ {
              "@type" : "C_ATTRIBUTE",
              "rmAttributeName" : "type",
              "children" : [ {
                "@type" : "C_STRING",
                "rmTypeName" : "STRING",
                "constraint" : [ "/urn:oid:1.2.752.29.4.19/" ]
              } ]
            } ],
            "attributeTuples" : [ ]
          } ]
        } ],
        "attributeTuples" : [ ]
      }, {
        "@type" : "C_COMPLEX_OBJECT",
        "rmTypeName" : "ELEMENT",
        "nodeId" : "at0004.1",
        "attributes" : [ {
          "@type" : "C_ATTRIBUTE",
          "rmAttributeName" : "value",
          "children" : [ {
            "@type" : "C_COMPLEX_OBJECT",
            "rmTypeName" : "DV_CODED_TEXT",
            "occurrences" : "1..1",
            "defaultValue" : {
              "defining_code" : {
                "terminology_id" : {
                  "value" : "local_terms",
                  "@type" : "TERMINOLOGY_ID"
                },
                "code_string" : "urn:oid:1.2.752.29.6.13",
                "@type" : "CODE_PHRASE"
              },
              "value" : "Vårdenhet",
              "@type" : "DV_CODED_TEXT"
            },
            "attributes" : [ {
              "@type" : "C_ATTRIBUTE",
              "rmAttributeName" : "defining_code",
              "children" : [ {
                "@type" : "C_TERMINOLOGY_CODE",
                "rmTypeName" : "TERMINOLOGY_CODE",
                "occurrences" : "0..1",
                "terminologyId" : {
                  "value" : "local_terms"
                },
                "constraint" : [ ],
                "selectedTerminologies" : [ "local_terms" ],
                "includedExternalTerminologyCodes" : [ {
                  "terminologyId" : "local_terms",
                  "code" : "urn:oid:1.2.752.29.6.13",
                  "value" : "Vårdenhet"
                } ]
              } ]
            } ],
            "attributeTuples" : [ ]
          } ]
        } ],
        "attributeTuples" : [ ]
      }, {
        "@type" : "C_COMPLEX_OBJECT",
        "rmTypeName" : "CLUSTER",
        "occurrences" : "0..0",
        "nodeId" : "at0006.1",
        "attributes" : [ ],
        "attributeTuples" : [ ]
      }, {
        "@type" : "C_COMPLEX_OBJECT",
        "rmTypeName" : "ELEMENT",
        "occurrences" : "0..0",
        "nodeId" : "at0019.1",
        "attributes" : [ ],
        "attributeTuples" : [ ]
      } ]
    } ],
    "attributeTuples" : [ ]
  },
  "terminology" : {
    "@type" : "ARCHETYPE_TERMINOLOGY",
    "conceptCode" : "at0000",
    "termDefinitions" : {
      "en" : {
        "at0000.1" : {
          "@type" : "ARCHETYPE_TERM",
          "code" : "at0000.1",
          "text" : "Care provider subunit",
          "description" : "An identified formal entity or informal grouping of people.",
          "comment" : "For example: a company, institution, corporation, department, community group, healthcare practice group, payer/insurer, care team, or a group of neighbours who will act as carers or support."
        },
        "at0003.1" : {
          "@type" : "ARCHETYPE_TERM",
          "code" : "at0003.1",
          "text" : "Identifier",
          "description" : "Identifier associated with the organisation, in Sweden usually a HSA-id",
          "comment" : "See https://openehr.atlassian.net/wiki/spaces/healthmod/pages/1922990156/HSA-identitet+och+Organisationsnummer"
        }
      },
      "nb" : {
        "at0000.1" : {
          "@type" : "ARCHETYPE_TERM",
          "code" : "at0000.1",
          "text" : "Care provider subunit",
          "description" : "En identifisert formell entitet eller en uformell gruppering av mennesker.",
          "comment" : "For eksempel: Et firma, institusjon, selskap, avdeling, gruppe i nærmiljøet, forsikringsselskap, behandlingsteam eller en gruppe av naboer som opptrer som støtte."
        }
      },
      "de" : {
        "at0000.1" : {
          "@type" : "ARCHETYPE_TERM",
          "code" : "at0000.1",
          "text" : "Care provider subunit",
          "description" : "Ein Unternehmen, eine Institution oder ein Verband, der in der Gesundheitsakte vertreten sein muss.",
          "comment" : "*For example: a company, institution, corporation, department, community group, healthcare practice group, payer/insurer, care team, or a group of neighbours who will act as carers or support.(en)"
        }
      },
      "sv" : {
        "at0000.1" : {
          "@type" : "ARCHETYPE_TERM",
          "code" : "at0000.1",
          "text" : "Vårdenhet",
          "description" : "In identifierad organisationsenhet eller en informell grupp.",
          "comment" : "Exempelvis företag, institution, avdeling, enhet, förening, vårdgivare, försäkringsbolag, vårdteam, eller en grupp grannar som fungerar som stöd."
        },
        "at0003.1" : {
          "@type" : "ARCHETYPE_TERM",
          "code" : "at0003.1",
          "text" : "Identifierare",
          "description" : "Identifierare associerad med den identifierade organisationen, i Sverige vanligen ett HSA-id",
          "comment" : "Se https://openehr.atlassian.net/wiki/spaces/healthmod/pages/1922990156/HSA-identitet+och+Organisationsnummer"
        }
      }
    },
    "termBindings" : { },
    "terminologyExtracts" : { },
    "valueSets" : { }
  },
  "adlVersion" : "1.4",
  "buildUid" : "71e23a66-f356-3b98-b030-a16b20226e77",
  "rmName" : "openehr",
  "rmRelease" : "1.1.0",
  "generated" : true,
  "templateId" : "Care provider",
  "otherMetaData" : { },
  "templateOverlays" : [ ],
  "originalLanguage" : {
    "terminologyId" : {
      "value" : "ISO_639-1"
    },
    "codeString" : "en"
  },
  "translations" : [ {
    "@type" : "TRANSLATION_DETAILS",
    "language" : {
      "terminologyId" : {
        "value" : "ISO_639-1"
      },
      "codeString" : "de"
    },
    "author" : { },
    "otherDetails" : { }
  }, {
    "@type" : "TRANSLATION_DETAILS",
    "language" : {
      "terminologyId" : {
        "value" : "ISO_639-1"
      },
      "codeString" : "sv"
    },
    "author" : { },
    "otherDetails" : { }
  }, {
    "@type" : "TRANSLATION_DETAILS",
    "language" : {
      "terminologyId" : {
        "value" : "ISO_639-1"
      },
      "codeString" : "nb"
    },
    "author" : { },
    "otherDetails" : { }
  } ]
}